{
  "manifest_version": 3,
  "name": "<%= name %>",
  "version": "<%= version %>",
  "description": "<%= description %>",
  "permissions": [
    "activeTab",
    "storage",
    "sidePanel"
  ],
  "host_permissions": <%= host_permissions.to_json %>,
  "background": {
    "service_worker": "background.js",
    "type": "module"
  },
  "content_scripts": [
    {
      "matches": <%= content_scripts_matches.to_json %>,
      "js": ["content.js"],
      "run_at": "document_idle"
    }
  ],
  "side_panel": {
    "default_path": "sidepanel.html"
  },
  "action": {
    "default_title": "Open DexIQ",
    "default_icon": {
      "16": "icons/icon16.png",
      "32": "icons/icon32.png",
      "48": "icons/icon48.png",
      "128": "icons/icon128.png"
    }
  },
  "icons": {
    "16": "icons/icon16.png",
    "32": "icons/icon32.png",
    "48": "icons/icon48.png",
    "128": "icons/icon128.png"
  }
}
